{
	"textures": [
		{
			"image": "npc28.png",
			"format": "RGBA8888",
			"size": {
				"w": 136,
				"h": 50
			},
			"scale": 1,
			"frames": [
				{
					"filename": "NPC 28-0.png",
					"rotated": false,
					"trimmed": false,
					"sourceSize": {
						"w": 32,
						"h": 48
					},
					"spriteSourceSize": {
						"x": 0,
						"y": 0,
						"w": 32,
						"h": 48
					},
					"frame": {
						"x": 1,
						"y": 1,
						"w": 32,
						"h": 48
					}
				},
				{
					"filename": "NPC 28-1.png",
					"rotated": false,
					"trimmed": false,
					"sourceSize": {
						"w": 32,
						"h": 48
					},
					"spriteSourceSize": {
						"x": 0,
						"y": 0,
						"w": 32,
						"h": 48
					},
					"frame": {
						"x": 1,
						"y": 1,
						"w": 32,
						"h": 48
					}
				},
				{
					"filename": "NPC 28-2.png",
					"rotated": false,
					"trimmed": false,
					"sourceSize": {
						"w": 32,
						"h": 48
					},
					"spriteSourceSize": {
						"x": 0,
						"y": 0,
						"w": 32,
						"h": 48
					},
					"frame": {
						"x": 1,
						"y": 1,
						"w": 32,
						"h": 48
					}
				},
				{
					"filename": "NPC 28-3.png",
					"rotated": false,
					"trimmed": false,
					"sourceSize": {
						"w": 32,
						"h": 48
					},
					"spriteSourceSize": {
						"x": 0,
						"y": 0,
						"w": 32,
						"h": 48
					},
					"frame": {
						"x": 1,
						"y": 1,
						"w": 32,
						"h": 48
					}
				},
				{
					"filename": "NPC 28-4.png",
					"rotated": false,
					"trimmed": false,
					"sourceSize": {
						"w": 32,
						"h": 48
					},
					"spriteSourceSize": {
						"x": 0,
						"y": 0,
						"w": 32,
						"h": 48
					},
					"frame": {
						"x": 35,
						"y": 1,
						"w": 32,
						"h": 48
					}
				},
				{
					"filename": "NPC 28-5.png",
					"rotated": false,
					"trimmed": false,
					"sourceSize": {
						"w": 32,
						"h": 48
					},
					"spriteSourceSize": {
						"x": 0,
						"y": 0,
						"w": 32,
						"h": 48
					},
					"frame": {
						"x": 35,
						"y": 1,
						"w": 32,
						"h": 48
					}
				},
				{
					"filename": "NPC 28-6.png",
					"rotated": false,
					"trimmed": false,
					"sourceSize": {
						"w": 32,
						"h": 48
					},
					"spriteSourceSize": {
						"x": 0,
						"y": 0,
						"w": 32,
						"h": 48
					},
					"frame": {
						"x": 35,
						"y": 1,
						"w": 32,
						"h": 48
					}
				},
				{
					"filename": "NPC 28-7.png",
					"rotated": false,
					"trimmed": false,
					"sourceSize": {
						"w": 32,
						"h": 48
					},
					"spriteSourceSize": {
						"x": 0,
						"y": 0,
						"w": 32,
						"h": 48
					},
					"frame": {
						"x": 35,
						"y": 1,
						"w": 32,
						"h": 48
					}
				},
				{
					"filename": "NPC 28-8.png",
					"rotated": false,
					"trimmed": false,
					"sourceSize": {
						"w": 32,
						"h": 48
					},
					"spriteSourceSize": {
						"x": 0,
						"y": 0,
						"w": 32,
						"h": 48
					},
					"frame": {
						"x": 69,
						"y": 1,
						"w": 32,
						"h": 48
					}
				},
				{
					"filename": "NPC 28-9.png",
					"rotated": false,
					"trimmed": false,
					"sourceSize": {
						"w": 32,
						"h": 48
					},
					"spriteSourceSize": {
						"x": 0,
						"y": 0,
						"w": 32,
						"h": 48
					},
					"frame": {
						"x": 69,
						"y": 1,
						"w": 32,
						"h": 48
					}
				},
				{
					"filename": "NPC 28-10.png",
					"rotated": false,
					"trimmed": false,
					"sourceSize": {
						"w": 32,
						"h": 48
					},
					"spriteSourceSize": {
						"x": 0,
						"y": 0,
						"w": 32,
						"h": 48
					},
					"frame": {
						"x": 69,
						"y": 1,
						"w": 32,
						"h": 48
					}
				},
				{
					"filename": "NPC 28-11.png",
					"rotated": false,
					"trimmed": false,
					"sourceSize": {
						"w": 32,
						"h": 48
					},
					"spriteSourceSize": {
						"x": 0,
						"y": 0,
						"w": 32,
						"h": 48
					},
					"frame": {
						"x": 69,
						"y": 1,
						"w": 32,
						"h": 48
					}
				},
				{
					"filename": "NPC 28-12.png",
					"rotated": false,
					"trimmed": false,
					"sourceSize": {
						"w": 32,
						"h": 48
					},
					"spriteSourceSize": {
						"x": 0,
						"y": 0,
						"w": 32,
						"h": 48
					},
					"frame": {
						"x": 103,
						"y": 1,
						"w": 32,
						"h": 48
					}
				},
				{
					"filename": "NPC 28-13.png",
					"rotated": false,
					"trimmed": false,
					"sourceSize": {
						"w": 32,
						"h": 48
					},
					"spriteSourceSize": {
						"x": 0,
						"y": 0,
						"w": 32,
						"h": 48
					},
					"frame": {
						"x": 103,
						"y": 1,
						"w": 32,
						"h": 48
					}
				},
				{
					"filename": "NPC 28-14.png",
					"rotated": false,
					"trimmed": false,
					"sourceSize": {
						"w": 32,
						"h": 48
					},
					"spriteSourceSize": {
						"x": 0,
						"y": 0,
						"w": 32,
						"h": 48
					},
					"frame": {
						"x": 103,
						"y": 1,
						"w": 32,
						"h": 48
					}
				},
				{
					"filename": "NPC 28-15.png",
					"rotated": false,
					"trimmed": false,
					"sourceSize": {
						"w": 32,
						"h": 48
					},
					"spriteSourceSize": {
						"x": 0,
						"y": 0,
						"w": 32,
						"h": 48
					},
					"frame": {
						"x": 103,
						"y": 1,
						"w": 32,
						"h": 48
					}
				}
			]
		}
	],
	"meta": {
		"app": "https://www.codeandweb.com/texturepacker",
		"version": "3.0",
		"smartupdate": "$TexturePacker:SmartUpdate:00ab6812ad9df6907c1f396f452738ae:85fe13d18a1348e0c5fb1d900fc77e8c:689916ce5fbb062ead9c148c36ca1fff$"
	}
}
